booookscore/__init__.py
booookscore/chunk.py
booookscore/postprocess.py
booookscore/score.py
booookscore/summ.py
booookscore/utils.py
booookscore-0.1.3.dist-info/LICENSE
booookscore-0.1.3.dist-info/METADATA
booookscore-0.1.3.dist-info/WHEEL
booookscore-0.1.3.dist-info/top_level.txt
booookscore-0.1.3.dist-info/RECORD
