Metadata-Version: 2.1
Name: booookscore
Version: 0.1.3
Summary: Official package for our ICLR 2024 paper, "BooookScore: A systematic exploration of book-length summarization in the era of LLMs".
Home-page: https://github.com/lilakk/BooookScore
Author: Yapei Chang
Author-email: yapeichang@umass.edu
License-File: LICENSE
Requires-Dist: anthropic ==0.21.3
Requires-Dist: fire ==0.5.0
Requires-Dist: nltk ==3.8.1
Requires-Dist: numpy ==1.23.1
Requires-Dist: openai ==1.16.1
Requires-Dist: scripts ==3.0
Requires-Dist: setuptools ==68.2.0
Requires-Dist: tiktoken ==0.5.2
Requires-Dist: torch ==1.13.1
Requires-Dist: tqdm ==4.66.1
Requires-Dist: transformers ==4.37.2
